falcon_signature/__init__.py
falcon_signature/common.py
falcon_signature/encoding.py
falcon_signature/falcon.py
falcon_signature/ffsampling.py
falcon_signature/fft.py
falcon_signature/fft_constants.py
falcon_signature/ntrugen.py
falcon_signature/ntt.py
falcon_signature/ntt_constants.py
falcon_signature/profile_action.py
falcon_signature/rng.py
falcon_signature/samplerz.py
falcon_signature/test.py
scripts/__init__.py
scripts/parameters.py
scripts/saga.py
scripts/samplerz_KAT1024.py
scripts/samplerz_KAT512.py
scripts/sign_KAT.py
falcon_signature-1.0.3.dist-info/LICENSE
falcon_signature-1.0.3.dist-info/METADATA
falcon_signature-1.0.3.dist-info/WHEEL
falcon_signature-1.0.3.dist-info/top_level.txt
falcon_signature-1.0.3.dist-info/RECORD
